dogfood_logger/__init__.py
dogfood_logger/logger.py
dogfood_logger/packageData/sampleData.dat
dogfood_logger-0.1.8.dist-info/LICENSE.txt
dogfood_logger-0.1.8.dist-info/METADATA
dogfood_logger-0.1.8.dist-info/WHEEL
dogfood_logger-0.1.8.dist-info/RECORD
